jenkins_auto_update/__init__.py
jenkins_auto_update/jenkinsautoupdater.py
jenkins_plugins_auto_update-1.0.1.dist-info/LICENSE
jenkins_plugins_auto_update-1.0.1.dist-info/METADATA
jenkins_plugins_auto_update-1.0.1.dist-info/WHEEL
jenkins_plugins_auto_update-1.0.1.dist-info/top_level.txt
jenkins_plugins_auto_update-1.0.1.dist-info/RECORD
