Metadata-Version: 2.1
Name: jenkins-plugins-auto-update
Version: 1.0.1
Summary: Updates Jenkins plugins with the magic of automation... and Selenium. 
Home-page: https://github.com/ThePotatoCamera/JenkinsPluginsAutoUpdate
Author: ThePotatoCamera
Author-email: alex0xela@outlook.com
License: UNKNOWN
Project-URL: Bug Tracker, https://github.com/ThePotatoCamera/JenkinsPluginsAutoUpdate/issues
Platform: UNKNOWN
Classifier: Programming Language :: Python :: 3
Classifier: License :: OSI Approved :: MIT License
Classifier: Operating System :: OS Independent
Requires-Python: >=3.7
License-File: LICENSE
